doubao_mcp_server.py
iflow_mcp_doubao_mcp_server-0.0.6.dist-info/METADATA
iflow_mcp_doubao_mcp_server-0.0.6.dist-info/WHEEL
iflow_mcp_doubao_mcp_server-0.0.6.dist-info/entry_points.txt
iflow_mcp_doubao_mcp_server-0.0.6.dist-info/RECORD
