Metadata-Version: 2.4
Name: iflow-mcp_doubao-mcp-server
Version: 0.0.6
Summary: 主要实现的是火山引擎的提供的豆包文生图、文生视频、图生视频MCP-Server
Author-email: wwzhouhui <75271002@qq.com>
Requires-Python: >=3.13
Requires-Dist: mcp[cli]>=1.9.4
Requires-Dist: openai>=1.86.0
Requires-Dist: requests>=2.31.0
